{
  "tables": [
    {
      "id": "RNVrhpA66tx3VAtO704OQ",
      "name": "Session",
      "x": -480,
      "y": -288,
      "locked": false,
      "fields": [
        {
          "name": "id",
          "type": "TEXT",
          "default": "",
          "check": "",
          "primary": true,
          "unique": true,
          "notNull": true,
          "increment": false,
          "comment": "",
          "id": "RfDln9dkKFxRYVqt69v8F",
          "size": "",
          "values": []
        },
        {
          "id": "4q68hIYhzn0FYAUwXZ6Hb",
          "name": "user_id",
          "type": "UUID",
          "default": "",
          "check": "",
          "primary": false,
          "unique": false,
          "notNull": true,
          "increment": false,
          "comment": "",
          "size": "",
          "values": []
        },
        {
          "id": "paNAPWIxSJmWE-2HrGlHH",
          "name": "expires_at",
          "type": "TIMESTAMPTZ",
          "default": "",
          "check": "",
          "primary": false,
          "unique": false,
          "notNull": true,
          "increment": false,
          "comment": "",
          "size": "",
          "values": []
        }
      ],
      "comment": "",
      "indices": [],
      "color": "#175e7a"
    },
    {
      "id": "fGGLyQhLvCYBYLPmwzSbB",
      "name": "User",
      "x": 24,
      "y": -168,
      "locked": false,
      "fields": [
        {
          "name": "id",
          "type": "UUID",
          "default": "",
          "check": "",
          "primary": true,
          "unique": true,
          "notNull": true,
          "increment": false,
          "comment": "",
          "id": "EBYEaFI9QBSG5s3PC-X6S",
          "size": "",
          "values": []
        },
        {
          "id": "brULJDXmSOwo0Ap6V6iK0",
          "name": "api_key",
          "type": "TEXT",
          "default": "",
          "check": "",
          "primary": false,
          "unique": true,
          "notNull": true,
          "increment": false,
          "comment": "",
          "size": "",
          "values": []
        },
        {
          "id": "VnY5VxwerbVCw4wR27K7y",
          "name": "email",
          "type": "TEXT",
          "default": "",
          "check": "",
          "primary": false,
          "unique": true,
          "notNull": true,
          "increment": false,
          "comment": "",
          "size": "",
          "values": []
        },
        {
          "id": "lt0fsbZKOImWkT2ixU1lK",
          "name": "password_hash",
          "type": "TEXT",
          "default": "",
          "check": "",
          "primary": false,
          "unique": false,
          "notNull": true,
          "increment": false,
          "comment": "",
          "size": "",
          "values": []
        },
        {
          "id": "0qnrZ1xCDRlCqhj7LH2Yl",
          "name": "online",
          "type": "BOOLEAN",
          "default": "",
          "check": "",
          "primary": false,
          "unique": false,
          "notNull": true,
          "increment": false,
          "comment": "",
          "size": "",
          "values": []
        },
        {
          "id": "8you0csimwfH_kImRgpnL",
          "name": "person",
          "type": "UUID",
          "default": "",
          "check": "",
          "primary": false,
          "unique": false,
          "notNull": false,
          "increment": false,
          "comment": "",
          "size": "",
          "values": []
        },
        {
          "id": "_fNYbyK_qm72C_HzJwZeA",
          "name": "association",
          "type": "UUID",
          "default": "",
          "check": "",
          "primary": false,
          "unique": false,
          "notNull": false,
          "increment": false,
          "comment": "",
          "size": "",
          "values": []
        }
      ],
      "comment": "Exactly one of person and association will be non null",
      "indices": [],
      "color": "#175e7a"
    },
    {
      "id": "qZCnA2OvWwWi2dEXNpA85",
      "name": "UsersPair",
      "x": -480,
      "y": 48,
      "locked": false,
      "fields": [
        {
          "id": "NBE2kKrrUxJGm5DP39qwt",
          "name": "id",
          "type": "UUID",
          "default": "",
          "check": "",
          "primary": true,
          "unique": true,
          "notNull": true,
          "increment": false,
          "comment": "",
          "size": "",
          "values": []
        },
        {
          "name": "left",
          "type": "UUID",
          "default": "",
          "check": "",
          "primary": false,
          "unique": false,
          "notNull": true,
          "increment": false,
          "comment": "",
          "id": "HOGVOK-3RyfjLdTgDQ5YR",
          "size": "",
          "values": []
        },
        {
          "id": "50XeWFTlq81K9ZQKR49l1",
          "name": "right",
          "type": "UUID",
          "default": "",
          "check": "",
          "primary": false,
          "unique": false,
          "notNull": true,
          "increment": false,
          "comment": "",
          "size": "",
          "values": []
        },
        {
          "id": "3JeYt7t2fKjXR0oqNyibR",
          "name": "friends",
          "type": "BOOLEAN",
          "default": "",
          "check": "",
          "primary": false,
          "unique": false,
          "notNull": true,
          "increment": false,
          "comment": "",
          "size": "",
          "values": []
        },
        {
          "id": "CsTOsZkVnePyvFZtzd2Xd",
          "name": "pending",
          "type": "UUID",
          "default": "",
          "check": "",
          "primary": false,
          "unique": false,
          "notNull": false,
          "increment": false,
          "comment": "",
          "size": "",
          "values": []
        }
      ],
      "comment": "",
      "indices": [],
      "color": "#175e7a"
    },
    {
      "id": "7PZi6XzOqw8_K8xvTP-6B",
      "name": "ChatMessage",
      "x": -984,
      "y": -192,
      "locked": false,
      "fields": [
        {
          "id": "bo80zGzT85BgK8ZOKrvIt",
          "name": "id",
          "type": "UUID",
          "default": "",
          "check": "",
          "primary": true,
          "unique": true,
          "notNull": true,
          "increment": false,
          "comment": "",
          "size": "",
          "values": []
        },
        {
          "name": "friends_id",
          "type": "UUID",
          "default": "",
          "check": "",
          "primary": false,
          "unique": false,
          "notNull": true,
          "increment": false,
          "comment": "",
          "id": "aa69SGUTuwPosrj50fn5H",
          "size": "",
          "values": []
        },
        {
          "id": "nf0nT_bxSSGgBl6b1742S",
          "name": "author",
          "type": "UUID",
          "default": "",
          "check": "",
          "primary": false,
          "unique": false,
          "notNull": true,
          "increment": false,
          "comment": "",
          "size": "",
          "values": []
        },
        {
          "id": "TiFsxiRKDv3WZtUs9U4W7",
          "name": "content",
          "type": "TEXT",
          "default": "",
          "check": "",
          "primary": false,
          "unique": false,
          "notNull": true,
          "increment": false,
          "comment": "",
          "size": "",
          "values": []
        },
        {
          "id": "HW5l-jJl85bMtnVWSxIsD",
          "name": "is_file",
          "type": "BOOLEAN",
          "default": "",
          "check": "",
          "primary": false,
          "unique": false,
          "notNull": true,
          "increment": false,
          "comment": "",
          "size": "",
          "values": []
        },
        {
          "id": "nPtqGadlRzfjuHm-FNMhx",
          "name": "read",
          "type": "BOOLEAN",
          "default": "",
          "check": "",
          "primary": false,
          "unique": false,
          "notNull": true,
          "increment": false,
          "comment": "",
          "size": "",
          "values": []
        },
        {
          "id": "XgBrZcgKqumgWIy46NltL",
          "name": "sent_at",
          "type": "TIMESTAMPTZ",
          "default": "",
          "check": "",
          "primary": false,
          "unique": false,
          "notNull": true,
          "increment": false,
          "comment": "",
          "size": "",
          "values": []
        }
      ],
      "comment": "",
      "indices": [],
      "color": "#175e7a"
    },
    {
      "id": "PpZOwXF6z3sxJ-lB3atNe",
      "name": "Pet",
      "x": 902.7751056640623,
      "y": -161.2923054945312,
      "locked": false,
      "fields": [
        {
          "name": "id",
          "type": "UUID",
          "default": "",
          "check": "",
          "primary": true,
          "unique": true,
          "notNull": true,
          "increment": false,
          "comment": "",
          "id": "v_nbggWWmamy1UqzacDJI",
          "size": "",
          "values": []
        },
        {
          "id": "zDaVNcoZpOzp8MkRyRodt",
          "name": "owner_id",
          "type": "UUID",
          "default": "",
          "check": "",
          "primary": false,
          "unique": false,
          "notNull": true,
          "increment": false,
          "comment": "",
          "size": "",
          "values": []
        },
        {
          "id": "6HaMUX1sWyAbMOsIkSu7o",
          "name": "name",
          "type": "TEXT",
          "default": "",
          "check": "",
          "primary": false,
          "unique": false,
          "notNull": true,
          "increment": false,
          "comment": "",
          "size": "",
          "values": []
        },
        {
          "id": "oH0uoFN7Zm0hNLmvv38w6",
          "name": "species",
          "type": "TEXT",
          "default": "",
          "check": "",
          "primary": false,
          "unique": false,
          "notNull": true,
          "increment": false,
          "comment": "",
          "size": "",
          "values": []
        },
        {
          "id": "Sr3QvsHY9E8kp9omLcjgj",
          "name": "breed",
          "type": "TEXT",
          "default": "",
          "check": "",
          "primary": false,
          "unique": false,
          "notNull": true,
          "increment": false,
          "comment": "",
          "size": "",
          "values": []
        },
        {
          "id": "xVI34tMXPQwgZu3lmm8_-",
          "name": "birth",
          "type": "TIMESTAMPTZ",
          "default": "",
          "check": "",
          "primary": false,
          "unique": false,
          "notNull": true,
          "increment": false,
          "comment": "",
          "size": "",
          "values": []
        },
        {
          "id": "hMlrPA9lsjbJPx7z9Ajqn",
          "name": "description",
          "type": "TEXT",
          "default": "",
          "check": "",
          "primary": false,
          "unique": false,
          "notNull": true,
          "increment": false,
          "comment": "",
          "size": "",
          "values": []
        },
        {
          "id": "AnA1Ea4jUujP8uF_Z4Xes",
          "name": "hasAvatar",
          "type": "BOOLEAN",
          "default": "",
          "check": "",
          "primary": false,
          "unique": false,
          "notNull": true,
          "increment": false,
          "comment": "",
          "size": "",
          "values": []
        }
      ],
      "comment": "",
      "indices": [],
      "color": "#175e7a"
    },
    {
      "id": "JprIBm6_OqSSgsniAK2uH",
      "name": "Post",
      "x": 912,
      "y": 240,
      "locked": false,
      "fields": [
        {
          "name": "id",
          "type": "UUID",
          "default": "",
          "check": "",
          "primary": true,
          "unique": true,
          "notNull": true,
          "increment": false,
          "comment": "",
          "id": "uOS6v3j5Zx5k_3OZqO2YI",
          "size": "",
          "values": []
        },
        {
          "id": "v5F5vz8I_89eMM-yTip8g",
          "name": "author",
          "type": "UUID",
          "default": "",
          "check": "",
          "primary": false,
          "unique": false,
          "notNull": true,
          "increment": false,
          "comment": "",
          "size": "",
          "values": []
        },
        {
          "id": "Q-3sZiI0ejguMTPdISq9E",
          "name": "content",
          "type": "TEXT",
          "default": "",
          "check": "",
          "primary": false,
          "unique": false,
          "notNull": true,
          "increment": false,
          "comment": "",
          "size": "",
          "values": []
        },
        {
          "id": "g1G_zjfbabLNT72wzWzVW",
          "name": "pet",
          "type": "UUID",
          "default": "",
          "check": "",
          "primary": false,
          "unique": false,
          "notNull": false,
          "increment": false,
          "comment": "",
          "size": "",
          "values": []
        },
        {
          "id": "6jqn_lkLWf7kVqekF4R2I",
          "name": "posted_at",
          "type": "TIMESTAMPTZ",
          "default": "",
          "check": "",
          "primary": false,
          "unique": false,
          "notNull": true,
          "increment": false,
          "comment": "",
          "size": "",
          "values": []
        }
      ],
      "comment": "",
      "indices": [],
      "color": "#175e7a"
    },
    {
      "id": "9PsyGff93nSPzU5HQXChM",
      "name": "City",
      "x": 966.5305811191953,
      "y": -661.9670219275956,
      "locked": false,
      "fields": [
        {
          "name": "code",
          "type": "TEXT",
          "default": "",
          "check": "",
          "primary": true,
          "unique": true,
          "notNull": true,
          "increment": false,
          "comment": "",
          "id": "iBGoSaWNoRXsNORB97c-o",
          "size": "",
          "values": []
        },
        {
          "id": "JT4x4uKEVYnspoFKxnAgk",
          "name": "name",
          "type": "TEXT",
          "default": "",
          "check": "",
          "primary": false,
          "unique": false,
          "notNull": true,
          "increment": false,
          "comment": "",
          "size": "",
          "values": []
        },
        {
          "id": "nMJUxY7fnawNZ-FARnQYr",
          "name": "location",
          "type": "POINT",
          "default": "",
          "check": "",
          "primary": false,
          "unique": false,
          "notNull": true,
          "increment": false,
          "comment": "",
          "size": "",
          "values": []
        }
      ],
      "comment": "",
      "indices": [],
      "color": "#175e7a"
    },
    {
      "id": "GaN1Qw61YOWxKnVhcfRyC",
      "name": "PostLike",
      "x": 496.14362751348057,
      "y": 348.960911192849,
      "locked": false,
      "fields": [
        {
          "id": "x4EEEMlxILsUU0fZdp-7v",
          "name": "post",
          "type": "UUID",
          "default": "",
          "check": "",
          "primary": true,
          "unique": false,
          "notNull": true,
          "increment": false,
          "comment": "",
          "size": "",
          "values": []
        },
        {
          "id": "eCOzXQiLqtKSaUB6UqroZ",
          "name": "user",
          "type": "UUID",
          "default": "",
          "check": "",
          "primary": true,
          "unique": false,
          "notNull": true,
          "increment": false,
          "comment": "",
          "size": "",
          "values": []
        }
      ],
      "comment": "",
      "indices": [],
      "color": "#175e7a"
    },
    {
      "id": "r5j8UAy_Be4PALMORtOHh",
      "name": "PostComment",
      "x": 497.83214674584787,
      "y": 541.7336690967552,
      "locked": false,
      "fields": [
        {
          "name": "id",
          "type": "UUID",
          "default": "",
          "check": "",
          "primary": true,
          "unique": true,
          "notNull": true,
          "increment": false,
          "comment": "",
          "id": "_8DICL4rRy8H1kI16PIkW",
          "size": "",
          "values": []
        },
        {
          "id": "6aJLFXHH1BS9KwnrMbjAJ",
          "name": "post",
          "type": "UUID",
          "default": "",
          "check": "",
          "primary": false,
          "unique": false,
          "notNull": true,
          "increment": false,
          "comment": "",
          "size": "",
          "values": []
        },
        {
          "id": "RpUHMmgapXJCD2LvHH6Xi",
          "name": "author",
          "type": "UUID",
          "default": "",
          "check": "",
          "primary": false,
          "unique": false,
          "notNull": true,
          "increment": false,
          "comment": "",
          "size": "",
          "values": []
        },
        {
          "id": "qyiAhGIW--qACIooMOAWW",
          "name": "content",
          "type": "TEXT",
          "default": "",
          "check": "",
          "primary": false,
          "unique": false,
          "notNull": true,
          "increment": false,
          "comment": "",
          "size": "",
          "values": []
        },
        {
          "id": "m8UrZGusErFk1iZXDJPDu",
          "name": "postedAt",
          "type": "TIMESTAMPTZ",
          "default": "",
          "check": "",
          "primary": false,
          "unique": false,
          "notNull": true,
          "increment": false,
          "comment": "",
          "size": "",
          "values": []
        }
      ],
      "comment": "",
      "indices": [],
      "color": "#175e7a"
    },
    {
      "id": "gByFuABozPqlYjtLSgiRi",
      "name": "Association",
      "x": 369.2767693910519,
      "y": -997.5136025290034,
      "locked": false,
      "fields": [
        {
          "name": "id",
          "type": "UUID",
          "default": "",
          "check": "",
          "primary": true,
          "unique": true,
          "notNull": true,
          "increment": false,
          "comment": "",
          "id": "K9Uz-g2Gd-wJixzrskdgy",
          "size": "",
          "values": []
        },
        {
          "id": "Yz3YpQ5isB_pyfRwUxWe-",
          "name": "name",
          "type": "TEXT",
          "default": "",
          "check": "",
          "primary": false,
          "unique": false,
          "notNull": true,
          "increment": false,
          "comment": "",
          "size": "",
          "values": []
        },
        {
          "id": "Uijb3uyfAO_QxxMBMiDd9",
          "name": "phone",
          "type": "TEXT",
          "default": "",
          "check": "",
          "primary": false,
          "unique": false,
          "notNull": true,
          "increment": false,
          "comment": "",
          "size": "",
          "values": []
        },
        {
          "id": "uMniMFKyiJ5sNrzgUC3b7",
          "name": "description",
          "type": "TEXT",
          "default": "",
          "check": "",
          "primary": false,
          "unique": false,
          "notNull": true,
          "increment": false,
          "comment": "",
          "size": "",
          "values": []
        },
        {
          "id": "-ODl14eRnlfQZkrwupabg",
          "name": "city",
          "type": "TEXT",
          "default": "",
          "check": "",
          "primary": false,
          "unique": false,
          "notNull": true,
          "increment": false,
          "comment": "",
          "size": "",
          "values": []
        },
        {
          "id": "D6AXe5Wxr3I3EmZM9ijOv",
          "name": "type",
          "type": "TEXT",
          "default": "",
          "check": "",
          "primary": false,
          "unique": false,
          "notNull": true,
          "increment": false,
          "comment": "",
          "size": "",
          "values": []
        },
        {
          "id": "jtwFd0jSGN_gdBVxWwpjG",
          "name": "has_avatar",
          "type": "BOOLEAN",
          "default": "",
          "check": "",
          "primary": false,
          "unique": false,
          "notNull": true,
          "increment": false,
          "comment": "",
          "size": "",
          "values": []
        },
        {
          "id": "1RKff6bRfArp9bVVcb0SG",
          "name": "foundedAt",
          "type": "TIMESTAMPTZ",
          "default": "",
          "check": "",
          "primary": false,
          "unique": false,
          "notNull": true,
          "increment": false,
          "comment": "",
          "size": "",
          "values": []
        }
      ],
      "comment": "",
      "indices": [],
      "color": "#175e7a"
    },
    {
      "id": "zIxBxixQNLc4WgeIrP3Ht",
      "name": "Person",
      "x": 369.8663968125,
      "y": -623.1444728906254,
      "locked": false,
      "fields": [
        {
          "name": "id",
          "type": "UUID",
          "default": "",
          "check": "",
          "primary": true,
          "unique": true,
          "notNull": true,
          "increment": false,
          "comment": "",
          "id": "YGmNJ_AVeumr2YchED98S",
          "size": "",
          "values": []
        },
        {
          "id": "yaY_0XU18FraYOKOAs-pO",
          "name": "first_name",
          "type": "TEXT",
          "default": "",
          "check": "",
          "primary": false,
          "unique": false,
          "notNull": true,
          "increment": false,
          "comment": "",
          "size": "",
          "values": []
        },
        {
          "id": "bPphCjOg_TqOi9rXDnCvI",
          "name": "last_name",
          "type": "TEXT",
          "default": "",
          "check": "",
          "primary": false,
          "unique": false,
          "notNull": true,
          "increment": false,
          "comment": "",
          "size": "",
          "values": []
        },
        {
          "id": "-nirGiEvwZfpf8aiNIJZ_",
          "name": "description",
          "type": "TEXT",
          "default": "",
          "check": "",
          "primary": false,
          "unique": false,
          "notNull": true,
          "increment": false,
          "comment": "",
          "size": "",
          "values": []
        },
        {
          "id": "i5Xcgw2O971TEYQMu-aJ6",
          "name": "city",
          "type": "TEXT",
          "default": "",
          "check": "",
          "primary": false,
          "unique": false,
          "notNull": true,
          "increment": false,
          "comment": "",
          "size": "",
          "values": []
        },
        {
          "id": "A0qqxJtPj-lP8UiNR-MZh",
          "name": "has_avatar",
          "type": "BOOLEAN",
          "default": "",
          "check": "",
          "primary": false,
          "unique": false,
          "notNull": true,
          "increment": false,
          "comment": "",
          "size": "",
          "values": []
        },
        {
          "id": "CmResaXekhmJP4NmuiAuG",
          "name": "joined_at",
          "type": "TIMESTAMPTZ",
          "default": "",
          "check": "",
          "primary": false,
          "unique": false,
          "notNull": true,
          "increment": false,
          "comment": "",
          "size": "",
          "values": []
        }
      ],
      "comment": "",
      "indices": [],
      "color": "#175e7a"
    }
  ],
  "relationships": [
    {
      "startTableId": "RNVrhpA66tx3VAtO704OQ",
      "startFieldId": "4q68hIYhzn0FYAUwXZ6Hb",
      "endTableId": "fGGLyQhLvCYBYLPmwzSbB",
      "endFieldId": "EBYEaFI9QBSG5s3PC-X6S",
      "cardinality": "many_to_one",
      "updateConstraint": "No action",
      "deleteConstraint": "No action",
      "name": "fk_Session_user_id_User",
      "id": "0rNlfO0Jjf6IbyDkuPFRc"
    },
    {
      "startTableId": "qZCnA2OvWwWi2dEXNpA85",
      "startFieldId": "HOGVOK-3RyfjLdTgDQ5YR",
      "endTableId": "fGGLyQhLvCYBYLPmwzSbB",
      "endFieldId": "EBYEaFI9QBSG5s3PC-X6S",
      "cardinality": "many_to_one",
      "updateConstraint": "No action",
      "deleteConstraint": "No action",
      "name": "fk_UsersPair_left_User",
      "id": "O3I6kDZot4IhFEN4fpdZf"
    },
    {
      "startTableId": "qZCnA2OvWwWi2dEXNpA85",
      "startFieldId": "50XeWFTlq81K9ZQKR49l1",
      "endTableId": "fGGLyQhLvCYBYLPmwzSbB",
      "endFieldId": "EBYEaFI9QBSG5s3PC-X6S",
      "cardinality": "many_to_one",
      "updateConstraint": "No action",
      "deleteConstraint": "No action",
      "name": "fk_UsersPair_right_User",
      "id": "-aMoGjUsSd5KyskrnMq1D"
    },
    {
      "startTableId": "7PZi6XzOqw8_K8xvTP-6B",
      "startFieldId": "aa69SGUTuwPosrj50fn5H",
      "endTableId": "qZCnA2OvWwWi2dEXNpA85",
      "endFieldId": "NBE2kKrrUxJGm5DP39qwt",
      "cardinality": "many_to_one",
      "updateConstraint": "No action",
      "deleteConstraint": "No action",
      "name": "fk_ChatMessage_friends_id_UsersPair",
      "id": "sPX-zV8IH8jw1qqmpUkLY"
    },
    {
      "startTableId": "PpZOwXF6z3sxJ-lB3atNe",
      "startFieldId": "zDaVNcoZpOzp8MkRyRodt",
      "endTableId": "fGGLyQhLvCYBYLPmwzSbB",
      "endFieldId": "EBYEaFI9QBSG5s3PC-X6S",
      "cardinality": "many_to_one",
      "updateConstraint": "No action",
      "deleteConstraint": "No action",
      "name": "fk_Pet_owner_id_User",
      "id": "1ktj8aXOsNLBVKNJ7X-DD"
    },
    {
      "startTableId": "JprIBm6_OqSSgsniAK2uH",
      "startFieldId": "v5F5vz8I_89eMM-yTip8g",
      "endTableId": "fGGLyQhLvCYBYLPmwzSbB",
      "endFieldId": "EBYEaFI9QBSG5s3PC-X6S",
      "cardinality": "many_to_one",
      "updateConstraint": "No action",
      "deleteConstraint": "No action",
      "name": "fk_Post_author_User",
      "id": "GTLVYamFWnTsDSExq03FQ"
    },
    {
      "startTableId": "qZCnA2OvWwWi2dEXNpA85",
      "startFieldId": "CsTOsZkVnePyvFZtzd2Xd",
      "endTableId": "fGGLyQhLvCYBYLPmwzSbB",
      "endFieldId": "EBYEaFI9QBSG5s3PC-X6S",
      "cardinality": "many_to_one",
      "updateConstraint": "No action",
      "deleteConstraint": "No action",
      "name": "fk_UsersPair_pending_User",
      "id": "xHtdc_97wVGU-CNGMntIE"
    },
    {
      "startTableId": "7PZi6XzOqw8_K8xvTP-6B",
      "startFieldId": "nf0nT_bxSSGgBl6b1742S",
      "endTableId": "fGGLyQhLvCYBYLPmwzSbB",
      "endFieldId": "EBYEaFI9QBSG5s3PC-X6S",
      "cardinality": "many_to_one",
      "updateConstraint": "No action",
      "deleteConstraint": "No action",
      "name": "fk_ChatMessage_author_User",
      "id": "JWdTgCY8GrjNnlTvGdgCJ"
    },
    {
      "startTableId": "GaN1Qw61YOWxKnVhcfRyC",
      "startFieldId": "x4EEEMlxILsUU0fZdp-7v",
      "endTableId": "JprIBm6_OqSSgsniAK2uH",
      "endFieldId": "uOS6v3j5Zx5k_3OZqO2YI",
      "cardinality": "many_to_one",
      "updateConstraint": "No action",
      "deleteConstraint": "No action",
      "name": "fk_PostLike_post_Post",
      "id": "1jNSBW-E0BrnJeQIL7we5"
    },
    {
      "startTableId": "GaN1Qw61YOWxKnVhcfRyC",
      "startFieldId": "eCOzXQiLqtKSaUB6UqroZ",
      "endTableId": "fGGLyQhLvCYBYLPmwzSbB",
      "endFieldId": "EBYEaFI9QBSG5s3PC-X6S",
      "cardinality": "many_to_one",
      "updateConstraint": "No action",
      "deleteConstraint": "No action",
      "name": "fk_PostLike_user_User",
      "id": "V9ToT1X0JPPU91WPFXq2V"
    },
    {
      "startTableId": "r5j8UAy_Be4PALMORtOHh",
      "startFieldId": "6aJLFXHH1BS9KwnrMbjAJ",
      "endTableId": "JprIBm6_OqSSgsniAK2uH",
      "endFieldId": "uOS6v3j5Zx5k_3OZqO2YI",
      "cardinality": "many_to_one",
      "updateConstraint": "No action",
      "deleteConstraint": "No action",
      "name": "fk_PostComment_post_Post",
      "id": "nhLWWXieiLSJ_E5Rb8Jzi"
    },
    {
      "startTableId": "r5j8UAy_Be4PALMORtOHh",
      "startFieldId": "RpUHMmgapXJCD2LvHH6Xi",
      "endTableId": "fGGLyQhLvCYBYLPmwzSbB",
      "endFieldId": "EBYEaFI9QBSG5s3PC-X6S",
      "cardinality": "many_to_one",
      "updateConstraint": "No action",
      "deleteConstraint": "No action",
      "name": "fk_PostComment_author_User",
      "id": "rpIS9jUL6oM9MyJxTAHEo"
    },
    {
      "startTableId": "gByFuABozPqlYjtLSgiRi",
      "startFieldId": "-ODl14eRnlfQZkrwupabg",
      "endTableId": "9PsyGff93nSPzU5HQXChM",
      "endFieldId": "iBGoSaWNoRXsNORB97c-o",
      "cardinality": "many_to_one",
      "updateConstraint": "No action",
      "deleteConstraint": "No action",
      "name": "fk_Association_city_City",
      "id": "lrJcKgGUzO0zNFvHJ-bSE"
    },
    {
      "startTableId": "zIxBxixQNLc4WgeIrP3Ht",
      "startFieldId": "i5Xcgw2O971TEYQMu-aJ6",
      "endTableId": "9PsyGff93nSPzU5HQXChM",
      "endFieldId": "iBGoSaWNoRXsNORB97c-o",
      "cardinality": "many_to_one",
      "updateConstraint": "No action",
      "deleteConstraint": "No action",
      "name": "fk_Person_city_City",
      "id": "SrcyQq-brJFkOuTzITdDl"
    },
    {
      "startTableId": "fGGLyQhLvCYBYLPmwzSbB",
      "startFieldId": "8you0csimwfH_kImRgpnL",
      "endTableId": "zIxBxixQNLc4WgeIrP3Ht",
      "endFieldId": "YGmNJ_AVeumr2YchED98S",
      "cardinality": "one_to_one",
      "updateConstraint": "No action",
      "deleteConstraint": "No action",
      "name": "fk_User_person_Person",
      "id": "sc94YmETJWQBe-xmQbtaj"
    },
    {
      "startTableId": "fGGLyQhLvCYBYLPmwzSbB",
      "startFieldId": "_fNYbyK_qm72C_HzJwZeA",
      "endTableId": "gByFuABozPqlYjtLSgiRi",
      "endFieldId": "K9Uz-g2Gd-wJixzrskdgy",
      "cardinality": "one_to_one",
      "updateConstraint": "No action",
      "deleteConstraint": "No action",
      "name": "fk_User_association_Association",
      "id": "dDxZVM1qFKfL-fcfWXhLV"
    },
    {
      "startTableId": "JprIBm6_OqSSgsniAK2uH",
      "startFieldId": "g1G_zjfbabLNT72wzWzVW",
      "endTableId": "PpZOwXF6z3sxJ-lB3atNe",
      "endFieldId": "v_nbggWWmamy1UqzacDJI",
      "cardinality": "many_to_one",
      "updateConstraint": "No action",
      "deleteConstraint": "No action",
      "name": "fk_Post_pet_Pet",
      "id": "yWBiHWh1hzfmbufZiHrpm"
    }
  ],
  "notes": [],
  "subjectAreas": [],
  "database": "postgresql",
  "types": [],
  "enums": [],
  "title": "Untitled Diagram"
}
